{"title":"JP Cart Cross Sell","type":["section"],"content":"Use this section to promote products on your cart page.","videoId":"","templates":["Cart"],"repoName":"Flex-Theme-Cart-Cross-Sell-Section","sectionPaths":[],"snippetPaths":[],"assetPaths":[],"available":true,"paid":true,"metafields":[],"compatibleWithAllThemes":true,"versions":[{"versions":[],"sectionPaths":[],"snippetPaths":[],"assetPaths":[],"_id":"6738f8ed4e29fba098844f4e"}],"_id":"6738f8ed4e29fba098844f4d","createdAt":"2024-11-16T19:56:29.803Z","updatedAt":"2024-11-16T19:56:29.803Z","__v":0}